kafkoroutine/__init__.py
kafkoroutine/consumer.py
kafkoroutine/producer.py
kafkoroutine-0.1.7.dist-info/LICENSE
kafkoroutine-0.1.7.dist-info/METADATA
kafkoroutine-0.1.7.dist-info/WHEEL
kafkoroutine-0.1.7.dist-info/RECORD
