Metadata-Version: 2.3
Name: kafkoroutine
Version: 0.1.7
Summary: ⚠️ This package is no longer maintained. No future updates will be released.
License: MIT
Author: Michal Polit
Author-email: mpolit@protonmail.com
Requires-Python: >=3.11,<4.0
Classifier: Development Status :: 7 - Inactive
Classifier: License :: OSI Approved :: MIT License
Classifier: Operating System :: OS Independent
Classifier: Programming Language :: Python :: 3
Classifier: Programming Language :: Python :: 3.11
Classifier: Programming Language :: Python :: 3.12
Classifier: Programming Language :: Python :: 3.13
Requires-Dist: kafka-python (>=2.0.2,<3.0.0)
Project-URL: Homepage, https://github.com/mpol1t/kafkoroutine
Project-URL: Repository, https://github.com/mpol1t/kafkoroutine
